zargunlite/__init__.py
zargunlite/_version.py
zargunlite/core.py
zargunlite/default_config.py
zargunlite/model.py
zargunlite/preprocess.py
zargunlite/py.typed
zargunlite-0.1.3.dist-info/LICENSE
zargunlite-0.1.3.dist-info/METADATA
zargunlite-0.1.3.dist-info/WHEEL
zargunlite-0.1.3.dist-info/top_level.txt
zargunlite-0.1.3.dist-info/RECORD
