Metadata-Version: 2.1
Name: zargunlite
Version: 0.1.3
Summary: a sigma rule detection engine based on sqlite
Author-email: hzqmwne <huangzhengqmwne@sina.cn>
License:                    GNU LESSER GENERAL PUBLIC LICENSE
Project-URL: Homepage, https://github.com/hzqmwne/zargunlite
Classifier: License :: OSI Approved :: GNU Lesser General Public License v3 (LGPLv3)
Classifier: Typing :: Typed
Classifier: Programming Language :: Python :: 3
Classifier: Programming Language :: Python :: 3.10
Classifier: Programming Language :: Python :: 3.11
Classifier: Programming Language :: Python :: 3.12
Classifier: Programming Language :: Python :: 3.13
Requires-Python: >=3.10
License-File: LICENSE
Provides-Extra: dev
Requires-Dist: flake8; extra == "dev"
Requires-Dist: Flake8-pyproject; extra == "dev"
Requires-Dist: black; extra == "dev"
Requires-Dist: isort; extra == "dev"
Requires-Dist: mypy>=1.11; extra == "dev"
Requires-Dist: pytest; extra == "dev"
Requires-Dist: coverage; extra == "dev"
